halib/__init__.py
halib/common.py
halib/csvfile.py
halib/cuda.py
halib/dataset.py
halib/filesys.py
halib/gdrive.py
halib/gdrive_mkdir.py
halib/gdrive_test.py
halib/jsonfile.py
halib/listop.py
halib/plot.py
halib/projectmake.py
halib/rich_color.py
halib/tele_noti.py
halib/textfile.py
halib/torchloader.py
halib/videofile.py
halib/common/__init__.py
halib/common/common.py
halib/common/rich_color.py
halib/exp/__init__.py
halib/exp/core/__init__.py
halib/exp/core/base_config.py
halib/exp/core/base_exp.py
halib/exp/core/param_gen.py
halib/exp/core/wandb_op.py
halib/exp/data/__init__.py
halib/exp/data/dataclass_util.py
halib/exp/data/dataset.py
halib/exp/data/torchloader.py
halib/exp/perf/__init__.py
halib/exp/perf/flop_calc.py
halib/exp/perf/gpu_mon.py
halib/exp/perf/perfcalc.py
halib/exp/perf/perfmetrics.py
halib/exp/perf/perftb.py
halib/exp/perf/profiler.py
halib/exp/viz/__init__.py
halib/exp/viz/plot.py
halib/filetype/__init__.py
halib/filetype/csvfile.py
halib/filetype/ipynb.py
halib/filetype/jsonfile.py
halib/filetype/textfile.py
halib/filetype/videofile.py
halib/filetype/yamlfile.py
halib/online/__init__.py
halib/online/gdrive.py
halib/online/gdrive_mkdir.py
halib/online/gdrive_test.py
halib/online/projectmake.py
halib/online/tele_noti.py
halib/research/__init__.py
halib/research/base_config.py
halib/research/base_exp.py
halib/research/benchquery.py
halib/research/dataset.py
halib/research/flop_csv.py
halib/research/flops.py
halib/research/metrics.py
halib/research/mics.py
halib/research/params_gen.py
halib/research/perfcalc.py
halib/research/perftb.py
halib/research/plot.py
halib/research/profiler.py
halib/research/torchloader.py
halib/research/wandb_op.py
halib/research/core/__init__.py
halib/research/core/base_config.py
halib/research/core/base_exp.py
halib/research/core/param_gen.py
halib/research/core/wandb_op.py
halib/research/data/__init__.py
halib/research/data/dataclass_util.py
halib/research/data/dataset.py
halib/research/data/torchloader.py
halib-0.2.32.dist-info/licenses/LICENSE.txt
halib-0.2.32.dist-info/METADATA
halib-0.2.32.dist-info/WHEEL
halib-0.2.32.dist-info/top_level.txt
halib-0.2.32.dist-info/RECORD
