Metadata-Version: 2.4
Name: halib
Version: 0.2.32
Summary: Small library for common tasks
Author: Hoang Van Ha
Author-email: hoangvanhauit@gmail.com
Classifier: Programming Language :: Python :: 3
Classifier: License :: OSI Approved :: MIT License
Classifier: Operating System :: OS Independent
Requires-Python: >=3.9
License-File: LICENSE.txt
Requires-Dist: arrow
Requires-Dist: click
Requires-Dist: dataclass-wizard
Requires-Dist: enlighten
Requires-Dist: itables
Requires-Dist: kaleido
Requires-Dist: loguru
Requires-Dist: matplotlib
Requires-Dist: more-itertools
Requires-Dist: moviepy
Requires-Dist: networkx
Requires-Dist: numpy
Requires-Dist: omegaconf
Requires-Dist: opencv-python
Requires-Dist: pandas
Requires-Dist: Pillow
Requires-Dist: plotly
Requires-Dist: Pyarrow
Requires-Dist: pycurl
Requires-Dist: pygwalker
Requires-Dist: python-telegram-bot
Requires-Dist: requests
Requires-Dist: rich
Requires-Dist: scikit-learn
Requires-Dist: seaborn
Requires-Dist: tabulate
Requires-Dist: timebudget
Requires-Dist: tqdm
Requires-Dist: tube_dl
Requires-Dist: wandb
Requires-Dist: ipynbname
Requires-Dist: typed-argument-parser
Requires-Dist: slack_sdk
Dynamic: author
Dynamic: author-email
Dynamic: classifier
Dynamic: description
Dynamic: description-content-type
Dynamic: license-file
Dynamic: requires-dist
Dynamic: requires-python
Dynamic: summary
